{
  "animation_count": 0,
  "armature_count": 0,
  "edge_count": 1830,
  "file_identifier": "https://github.com/fazhihe/WHUCAD/blob/main/data/brep/0100/100001341.stl",
  "file_size": 331936,
  "lamp_count": 1,
  "linked_files": [],
  "material_count": 0,
  "mesh_count": 1,
  "metadata": {
    "github_organization": "fazhihe",
    "github_repo": "WHUCAD"
  },
  "missing_textures": {
    "count": 0,
    "file_path_to_color": {},
    "files": []
  },
  "object_count": 4,
  "poly_count": 1220,
  "random_color": [
    0.8,
    0.8,
    0.8,
    1
  ],
  "save_uid": "100001341.stl",
  "scene_size": {
    "bbox_max": [
      0.1875,
      0.1855262964963913,
      0.3720394968986511
    ],
    "bbox_min": [
      -2.845859972696018e-17,
      -0.1875,
      -0.37401318550109863
    ]
  },
  "sha256": "a8557d59cc290296b3f1b20af30cd9a7b7abf35091905449a1881be9e44c2676",
  "shape_key_count": 0,
  "vert_count": 612
}