{
  "animation_count": 0,
  "armature_count": 0,
  "edge_count": 30,
  "file_identifier": "https://github.com/Gardenia33/dataset_stl-obj/blob/main/cad_obj_test_fushion360gallery_reconstruction/131065_c82633e9_0000.obj",
  "file_size": 1578,
  "lamp_count": 1,
  "linked_files": [],
  "material_count": 1,
  "mesh_count": 1,
  "metadata": {
    "github_organization": "Gardenia33",
    "github_repo": "dataset_stl-obj"
  },
  "missing_textures": {
    "count": 0,
    "file_path_to_color": {},
    "files": []
  },
  "object_count": 4,
  "poly_count": 12,
  "random_color": null,
  "save_uid": "131065_c82633e9_0000",
  "scene_size": {
    "bbox_max": [
      3.9000000953674316,
      0.0,
      0.15000000596046448
    ],
    "bbox_min": [
      0.0,
      -2.700000047683716,
      -1.1802075050582062e-07
    ]
  },
  "sha256": "6dd6b1acfd5a495e17d208bf5df535519b65fc12369aa1eba99e5ceba30895f8",
  "shape_key_count": 0,
  "vert_count": 24
}