{
  "animation_count": 0,
  "armature_count": 0,
  "edge_count": 1512,
  "file_identifier": "https://github.com/Gardenia33/dataset_stl-obj/blob/main/cad_json_stl_output/0070/00709571.stl",
  "file_size": 50484,
  "lamp_count": 1,
  "linked_files": [],
  "material_count": 0,
  "mesh_count": 1,
  "metadata": {
    "github_organization": "Gardenia33",
    "github_repo": "dataset_stl-obj"
  },
  "missing_textures": {
    "count": 0,
    "file_path_to_color": {},
    "files": []
  },
  "object_count": 4,
  "poly_count": 1008,
  "random_color": [
    0.8,
    0.8,
    0.8,
    1
  ],
  "save_uid": "00709571.stl",
  "scene_size": {
    "bbox_max": [
      0.445419579744339,
      4.2288614876549496e-16,
      0.75
    ],
    "bbox_min": [
      -0.5402674078941345,
      -0.332329660654068,
      -0.383516401052475
    ]
  },
  "sha256": "5c7510dc52de74031767af3ee14a1e04e01bff25b878c16ccb24da3e8dcbb98a",
  "shape_key_count": 0,
  "vert_count": 502
}