{
  "animation_count": 0,
  "armature_count": 0,
  "edge_count": 1416,
  "file_identifier": "https://github.com/Gardenia33/dataset_stl-obj/blob/main/cad_json_stl_output/0068/00682055.stl",
  "file_size": 47284,
  "lamp_count": 1,
  "linked_files": [],
  "material_count": 0,
  "mesh_count": 1,
  "metadata": {
    "github_organization": "Gardenia33",
    "github_repo": "dataset_stl-obj"
  },
  "missing_textures": {
    "count": 0,
    "file_path_to_color": {},
    "files": []
  },
  "object_count": 4,
  "poly_count": 944,
  "random_color": [
    0.8,
    0.8,
    0.8,
    1
  ],
  "save_uid": "00682055.stl",
  "scene_size": {
    "bbox_max": [
      0.3610594868659973,
      2.8276786751810007e-16,
      0.7500000596046448
    ],
    "bbox_min": [
      -0.7221189737319946,
      -0.7221189737319946,
      -0.1526487022638321
    ]
  },
  "sha256": "5350e2e4cdc46384ab886b0c783aed8ae52915c775be74c4244c759b8648de99",
  "shape_key_count": 0,
  "vert_count": 472
}