{
  "animation_count": 0,
  "armature_count": 0,
  "edge_count": 30,
  "file_identifier": "https://github.com/Gardenia33/dataset_stl-obj/blob/main/cad_json_stl_output/0010/00104494.stl",
  "file_size": 1084,
  "lamp_count": 1,
  "linked_files": [],
  "material_count": 0,
  "mesh_count": 1,
  "metadata": {
    "github_organization": "Gardenia33",
    "github_repo": "dataset_stl-obj"
  },
  "missing_textures": {
    "count": 0,
    "file_path_to_color": {},
    "files": []
  },
  "object_count": 4,
  "poly_count": 20,
  "random_color": [
    0.8,
    0.8,
    0.8,
    1
  ],
  "save_uid": "00104494.stl",
  "scene_size": {
    "bbox_max": [
      0.75,
      0.34949880838394165,
      0.3310922086238861
    ],
    "bbox_min": [
      -0.30949509143829346,
      -0.18024873733520508,
      -1.103705188814096e-17
    ]
  },
  "sha256": "73367898bfd3a984e5694e982df5e504d4a0714fa4c377c8f20f9e4bbb657f22",
  "shape_key_count": 0,
  "vert_count": 12
}