{
  "animation_count": 0,
  "armature_count": 0,
  "edge_count": 600,
  "file_identifier": "https://github.com/fazhihe/WHUCAD/blob/main/data/brep/0101/100002286.stl",
  "file_size": 108899,
  "lamp_count": 1,
  "linked_files": [],
  "material_count": 0,
  "mesh_count": 1,
  "metadata": {
    "github_organization": "fazhihe",
    "github_repo": "WHUCAD"
  },
  "missing_textures": {
    "count": 0,
    "file_path_to_color": {},
    "files": []
  },
  "object_count": 4,
  "poly_count": 400,
  "random_color": [
    0.8,
    0.8,
    0.8,
    1
  ],
  "save_uid": "100002286.stl",
  "scene_size": {
    "bbox_max": [
      0.13560859858989716,
      0.1342104971408844,
      0.1484375
    ],
    "bbox_min": [
      -0.1328125,
      -0.1342104971408844,
      -0.6013813018798828
    ]
  },
  "sha256": "1a744251aa7b9adf249f0974d0ad4c5dfa970058cb4b57baa57be04a29a94b30",
  "shape_key_count": 0,
  "vert_count": 202
}