{
  "animation_count": 0,
  "armature_count": 0,
  "edge_count": 408,
  "file_identifier": "https://github.com/fazhihe/WHUCAD/blob/main/data/brep/0101/100001462.stl",
  "file_size": 74107,
  "lamp_count": 1,
  "linked_files": [],
  "material_count": 0,
  "mesh_count": 1,
  "metadata": {
    "github_organization": "fazhihe",
    "github_repo": "WHUCAD"
  },
  "missing_textures": {
    "count": 0,
    "file_path_to_color": {},
    "files": []
  },
  "object_count": 4,
  "poly_count": 272,
  "random_color": [
    0.8,
    0.8,
    0.8,
    1
  ],
  "save_uid": "100001462.stl",
  "scene_size": {
    "bbox_max": [
      0.6015625,
      0.19457240402698517,
      0.0390625
    ],
    "bbox_min": [
      -0.1484375,
      -0.484375,
      0.0
    ]
  },
  "sha256": "b89b5ecfd86555951acf1c73339a42494a1717dbf2d422d151a6ebc7b06c4685",
  "shape_key_count": 0,
  "vert_count": 140
}