{
  "animation_count": 0,
  "armature_count": 0,
  "edge_count": 18,
  "file_identifier": "https://github.com/Gardenia33/dataset_stl-obj/blob/main/cad_json_stl_output/0033/00337011.stl",
  "file_size": 684,
  "lamp_count": 1,
  "linked_files": [],
  "material_count": 0,
  "mesh_count": 1,
  "metadata": {
    "github_organization": "Gardenia33",
    "github_repo": "dataset_stl-obj"
  },
  "missing_textures": {
    "count": 0,
    "file_path_to_color": {},
    "files": []
  },
  "object_count": 4,
  "poly_count": 12,
  "random_color": [
    0.8,
    0.8,
    0.8,
    1
  ],
  "save_uid": "00337011.stl",
  "scene_size": {
    "bbox_max": [
      0.3650057315826416,
      3.465403693119455e-16,
      0.75
    ],
    "bbox_min": [
      -0.030534204095602036,
      -0.016480831429362297,
      -0.041079871356487274
    ]
  },
  "sha256": "26b8656ae07ba911e56d6bb2796d85805c11b8951610ce58701047f81cbd2527",
  "shape_key_count": 0,
  "vert_count": 8
}