{
  "animation_count": 0,
  "armature_count": 0,
  "edge_count": 2481,
  "file_identifier": "https://github.com/fazhihe/WHUCAD/blob/main/data/brep/0100/100000468.stl",
  "file_size": 450356,
  "lamp_count": 1,
  "linked_files": [],
  "material_count": 0,
  "mesh_count": 1,
  "metadata": {
    "github_organization": "fazhihe",
    "github_repo": "WHUCAD"
  },
  "missing_textures": {
    "count": 0,
    "file_path_to_color": {},
    "files": []
  },
  "object_count": 4,
  "poly_count": 1654,
  "random_color": [
    0.8,
    0.8,
    0.8,
    1
  ],
  "save_uid": "100000468.stl",
  "scene_size": {
    "bbox_max": [
      0.37835559248924255,
      0.171875,
      0.1328125
    ],
    "bbox_min": [
      -0.3768754005432129,
      -0.1796875,
      0.0
    ]
  },
  "sha256": "8ec503099a7811f8ac9b9f2eccf4196de66d2fb5a9ea514edcaf0da80ac422cf",
  "shape_key_count": 0,
  "vert_count": 815
}