{
  "animation_count": 0,
  "armature_count": 0,
  "edge_count": 18,
  "file_identifier": "https://github.com/Gardenia33/dataset_stl-obj/blob/main/cad_json_stl_output/0064/00641690.stl",
  "file_size": 684,
  "lamp_count": 1,
  "linked_files": [],
  "material_count": 0,
  "mesh_count": 1,
  "metadata": {
    "github_organization": "Gardenia33",
    "github_repo": "dataset_stl-obj"
  },
  "missing_textures": {
    "count": 0,
    "file_path_to_color": {},
    "files": []
  },
  "object_count": 4,
  "poly_count": 12,
  "random_color": [
    0.8,
    0.8,
    0.8,
    1
  ],
  "save_uid": "00641690.stl",
  "scene_size": {
    "bbox_max": [
      7.1205808829065e-16,
      0.0,
      0.7078765630722046
    ],
    "bbox_min": [
      -0.7078765630722046,
      -0.75,
      0.0
    ]
  },
  "sha256": "0bfac9d64697a0ab9e95916e472e2f11a9e304b4819d0929e7671ba0fac09ea1",
  "shape_key_count": 0,
  "vert_count": 8
}