{
  "animation_count": 0,
  "armature_count": 0,
  "edge_count": 1110,
  "file_identifier": "https://github.com/fazhihe/WHUCAD/blob/main/data/brep/0101/100001589.stl",
  "file_size": 201455,
  "lamp_count": 1,
  "linked_files": [],
  "material_count": 0,
  "mesh_count": 1,
  "metadata": {
    "github_organization": "fazhihe",
    "github_repo": "WHUCAD"
  },
  "missing_textures": {
    "count": 0,
    "file_path_to_color": {},
    "files": []
  },
  "object_count": 4,
  "poly_count": 740,
  "random_color": [
    0.8,
    0.8,
    0.8,
    1
  ],
  "save_uid": "100001589.stl",
  "scene_size": {
    "bbox_max": [
      0.75,
      0.3236841857433319,
      0.5546875
    ],
    "bbox_min": [
      0.0,
      -3.666658059642587e-17,
      0.0
    ]
  },
  "sha256": "a1d19edd5a34bc74f11a98c6eb973ffe382924179b0f87901934e1416ec1a493",
  "shape_key_count": 0,
  "vert_count": 366
}