{
  "animation_count": 0,
  "armature_count": 0,
  "edge_count": 77,
  "file_identifier": "https://github.com/Gardenia33/dataset_stl-obj/blob/main/cad_json_stl_output/0007/00073880.stl",
  "file_size": 2684,
  "lamp_count": 1,
  "linked_files": [],
  "material_count": 0,
  "mesh_count": 1,
  "metadata": {
    "github_organization": "Gardenia33",
    "github_repo": "dataset_stl-obj"
  },
  "missing_textures": {
    "count": 0,
    "file_path_to_color": {},
    "files": []
  },
  "object_count": 4,
  "poly_count": 52,
  "random_color": [
    0.8,
    0.8,
    0.8,
    1
  ],
  "save_uid": "00073880.stl",
  "scene_size": {
    "bbox_max": [
      1.3351088824577442e-17,
      0.7359374761581421,
      0.75
    ],
    "bbox_min": [
      -0.7640625238418579,
      -0.75,
      -1.6739452885910648e-16
    ]
  },
  "sha256": "a8e752daf26c84e19adaae05c7f3a64ec6aa7ec060eaa269f6f1dfb010d268a3",
  "shape_key_count": 0,
  "vert_count": 28
}