{
  "animation_count": 0,
  "armature_count": 0,
  "edge_count": 36,
  "file_identifier": "https://github.com/Gardenia33/dataset_stl-obj/blob/main/cad_json_stl_output/0063/00636059.stl",
  "file_size": 1284,
  "lamp_count": 1,
  "linked_files": [],
  "material_count": 0,
  "mesh_count": 1,
  "metadata": {
    "github_organization": "Gardenia33",
    "github_repo": "dataset_stl-obj"
  },
  "missing_textures": {
    "count": 0,
    "file_path_to_color": {},
    "files": []
  },
  "object_count": 4,
  "poly_count": 24,
  "random_color": [
    0.8,
    0.8,
    0.8,
    1
  ],
  "save_uid": "00636059.stl",
  "scene_size": {
    "bbox_max": [
      0.75,
      0.18457944691181183,
      0.36915889382362366
    ],
    "bbox_min": [
      -0.4306853711605072,
      -0.18457944691181183,
      -1.1302231103274434e-17
    ]
  },
  "sha256": "f180cf3378381558056a0b4337de553f64bc22d599285e954f0f4f7bb6c131d5",
  "shape_key_count": 0,
  "vert_count": 16
}