{
  "animation_count": 0,
  "armature_count": 0,
  "edge_count": 192,
  "file_identifier": "https://github.com/fazhihe/WHUCAD/blob/main/data/brep/0101/100001901.stl",
  "file_size": 34851,
  "lamp_count": 1,
  "linked_files": [],
  "material_count": 0,
  "mesh_count": 1,
  "metadata": {
    "github_organization": "fazhihe",
    "github_repo": "WHUCAD"
  },
  "missing_textures": {
    "count": 0,
    "file_path_to_color": {},
    "files": []
  },
  "object_count": 4,
  "poly_count": 128,
  "random_color": [
    0.8,
    0.8,
    0.8,
    1
  ],
  "save_uid": "100001901.stl",
  "scene_size": {
    "bbox_max": [
      0.0007498214836232364,
      0.432481586933136,
      0.049067359417676926
    ],
    "bbox_min": [
      -0.32012939453125,
      -0.3203125,
      -0.049067359417676926
    ]
  },
  "sha256": "14c4370b588b6b6eb69db5f1f8ccabcb81571a36b83fb04977dd6f85a4ea4e55",
  "shape_key_count": 0,
  "vert_count": 66
}