{
  "animation_count": 0,
  "armature_count": 0,
  "edge_count": 84,
  "file_identifier": "https://github.com/Gardenia33/dataset_stl-obj/blob/main/cad_json_stl_output/0005/00050760.stl",
  "file_size": 2884,
  "lamp_count": 1,
  "linked_files": [],
  "material_count": 0,
  "mesh_count": 1,
  "metadata": {
    "github_organization": "Gardenia33",
    "github_repo": "dataset_stl-obj"
  },
  "missing_textures": {
    "count": 0,
    "file_path_to_color": {},
    "files": []
  },
  "object_count": 4,
  "poly_count": 56,
  "random_color": [
    0.8,
    0.8,
    0.8,
    1
  ],
  "save_uid": "00050760.stl",
  "scene_size": {
    "bbox_max": [
      0.05314960703253746,
      0.05314960703253746,
      0.15000000596046448
    ],
    "bbox_min": [
      0.0,
      0.0,
      0.0
    ]
  },
  "sha256": "f709572106de5933fcb8284b3a472fb2381274d870bbf1c9b890e57192dfcffb",
  "shape_key_count": 0,
  "vert_count": 28
}