{
  "animation_count": 0,
  "armature_count": 0,
  "edge_count": 444,
  "file_identifier": "https://github.com/Gardenia33/dataset_stl-obj/blob/main/cad_json_stl_output/0074/00743651.stl",
  "file_size": 14884,
  "lamp_count": 1,
  "linked_files": [],
  "material_count": 0,
  "mesh_count": 1,
  "metadata": {
    "github_organization": "Gardenia33",
    "github_repo": "dataset_stl-obj"
  },
  "missing_textures": {
    "count": 0,
    "file_path_to_color": {},
    "files": []
  },
  "object_count": 4,
  "poly_count": 296,
  "random_color": [
    0.8,
    0.8,
    0.8,
    1
  ],
  "save_uid": "00743651.stl",
  "scene_size": {
    "bbox_max": [
      0.11903571337461472,
      0.13745057582855225,
      0.75
    ],
    "bbox_min": [
      -0.11903571337461472,
      -0.13745057582855225,
      -8.416420457661697e-18
    ]
  },
  "sha256": "58a0cd891b94227f9540abe8c10e1eadf30c9d0ba65b06f598915d56d6771f4c",
  "shape_key_count": 0,
  "vert_count": 148
}