{
  "animation_count": 0,
  "armature_count": 0,
  "edge_count": 126,
  "file_identifier": "https://github.com/Gardenia33/dataset_stl-obj/blob/main/cad_json_stl_output/0040/00409751.stl",
  "file_size": 4284,
  "lamp_count": 1,
  "linked_files": [],
  "material_count": 0,
  "mesh_count": 1,
  "metadata": {
    "github_organization": "Gardenia33",
    "github_repo": "dataset_stl-obj"
  },
  "missing_textures": {
    "count": 0,
    "file_path_to_color": {},
    "files": []
  },
  "object_count": 4,
  "poly_count": 84,
  "random_color": [
    0.8,
    0.8,
    0.8,
    1
  ],
  "save_uid": "00409751.stl",
  "scene_size": {
    "bbox_max": [
      0.054752152413129807,
      0.2697630822658539,
      0.04411764815449715
    ],
    "bbox_min": [
      -0.4892638623714447,
      -0.28722408413887024,
      -0.44823530316352844
    ]
  },
  "sha256": "1ccff60874490913ad1757934c531871620330351852dae37c29d5905eee9889",
  "shape_key_count": 0,
  "vert_count": 44
}