{
  "animation_count": 0,
  "armature_count": 0,
  "edge_count": 60,
  "file_identifier": "https://github.com/Gardenia33/dataset_stl-obj/blob/main/cad_json_stl_output/0033/00338132.stl",
  "file_size": 2084,
  "lamp_count": 1,
  "linked_files": [],
  "material_count": 0,
  "mesh_count": 1,
  "metadata": {
    "github_organization": "Gardenia33",
    "github_repo": "dataset_stl-obj"
  },
  "missing_textures": {
    "count": 0,
    "file_path_to_color": {},
    "files": []
  },
  "object_count": 4,
  "poly_count": 40,
  "random_color": [
    0.8,
    0.8,
    0.8,
    1
  ],
  "save_uid": "00338132.stl",
  "scene_size": {
    "bbox_max": [
      0.75,
      7.1205808829065e-16,
      0.01406249962747097
    ],
    "bbox_min": [
      -0.75,
      -0.5625,
      -0.01406249962747097
    ]
  },
  "sha256": "680e84a8b7a69c2d8afeabb4d2c0fa64d06df2e6d363e1f94a2db1b1fdb161d7",
  "shape_key_count": 0,
  "vert_count": 22
}