{
  "animation_count": 0,
  "armature_count": 0,
  "edge_count": 102,
  "file_identifier": "https://github.com/Gardenia33/dataset_stl-obj/blob/main/cad_obj_test_fushion360gallery_reconstruction/35145_a3d7363c_0015.obj",
  "file_size": 4526,
  "lamp_count": 1,
  "linked_files": [],
  "material_count": 1,
  "mesh_count": 1,
  "metadata": {
    "github_organization": "Gardenia33",
    "github_repo": "dataset_stl-obj"
  },
  "missing_textures": {
    "count": 0,
    "file_path_to_color": {},
    "files": []
  },
  "object_count": 4,
  "poly_count": 44,
  "random_color": null,
  "save_uid": "35145_a3d7363c_0015",
  "scene_size": {
    "bbox_max": [
      5.0,
      2.200000047683716,
      6.199999809265137
    ],
    "bbox_min": [
      -5.0,
      -2.200000286102295,
      -2.200000047683716
    ]
  },
  "sha256": "4d7b0bd9ab257961220c0145da1f1da3ca3cb65d17fc6193295282d74b8595c6",
  "shape_key_count": 0,
  "vert_count": 72
}