{
  "animation_count": 0,
  "armature_count": 0,
  "edge_count": 1152,
  "file_identifier": "https://github.com/fazhihe/WHUCAD/blob/main/data/brep/0100/100000058.stl",
  "file_size": 208996,
  "lamp_count": 1,
  "linked_files": [],
  "material_count": 0,
  "mesh_count": 1,
  "metadata": {
    "github_organization": "fazhihe",
    "github_repo": "WHUCAD"
  },
  "missing_textures": {
    "count": 0,
    "file_path_to_color": {},
    "files": []
  },
  "object_count": 4,
  "poly_count": 768,
  "random_color": [
    0.8,
    0.8,
    0.8,
    1
  ],
  "save_uid": "100000058.stl",
  "scene_size": {
    "bbox_max": [
      0.3270559012889862,
      0.3236841857433319,
      0.75
    ],
    "bbox_min": [
      -0.3203125,
      -0.3236841857433319,
      0.0
    ]
  },
  "sha256": "903d9e77297bd5a75b33f1388fdacb14766f58bdb2910a34609120909abaa023",
  "shape_key_count": 0,
  "vert_count": 380
}