{
  "animation_count": 0,
  "armature_count": 0,
  "edge_count": 66,
  "file_identifier": "https://github.com/Gardenia33/dataset_stl-obj/blob/main/cad_json_stl_output/0035/00351921.stl",
  "file_size": 2284,
  "lamp_count": 1,
  "linked_files": [],
  "material_count": 0,
  "mesh_count": 1,
  "metadata": {
    "github_organization": "Gardenia33",
    "github_repo": "dataset_stl-obj"
  },
  "missing_textures": {
    "count": 0,
    "file_path_to_color": {},
    "files": []
  },
  "object_count": 4,
  "poly_count": 44,
  "random_color": [
    0.8,
    0.8,
    0.8,
    1
  ],
  "save_uid": "00351921.stl",
  "scene_size": {
    "bbox_max": [
      0.5408432483673096,
      0.1971723586320877,
      0.10647954046726227
    ],
    "bbox_min": [
      -0.5937256813049316,
      -0.75,
      -4.5924253663221344e-17
    ]
  },
  "sha256": "6d6d347bedd399884fe4a00ece3b57c2a65ecf03b8ab8cd61b4420b224ea5f3f",
  "shape_key_count": 0,
  "vert_count": 24
}