{
  "animation_count": 0,
  "armature_count": 0,
  "edge_count": 1557,
  "file_identifier": "https://github.com/fazhihe/WHUCAD/blob/main/data/brep/0101/100001682.stl",
  "file_size": 282431,
  "lamp_count": 1,
  "linked_files": [],
  "material_count": 0,
  "mesh_count": 1,
  "metadata": {
    "github_organization": "fazhihe",
    "github_repo": "WHUCAD"
  },
  "missing_textures": {
    "count": 0,
    "file_path_to_color": {},
    "files": []
  },
  "object_count": 4,
  "poly_count": 1037,
  "random_color": [
    0.8,
    0.8,
    0.8,
    1
  ],
  "save_uid": "100001682.stl",
  "scene_size": {
    "bbox_max": [
      0.75,
      0.504522979259491,
      0.3359375
    ],
    "bbox_min": [
      0.0,
      0.007154604885727167,
      0.0
    ]
  },
  "sha256": "8415a34560a6e0d700c806a694eed1b7602fc7af4046d78664e73dbf8314e7a5",
  "shape_key_count": 0,
  "vert_count": 511
}