{
  "animation_count": 0,
  "armature_count": 0,
  "edge_count": 420,
  "file_identifier": "https://github.com/Gardenia33/dataset_stl-obj/blob/main/cad_json_stl_output/0061/00615912.stl",
  "file_size": 14084,
  "lamp_count": 1,
  "linked_files": [],
  "material_count": 0,
  "mesh_count": 1,
  "metadata": {
    "github_organization": "Gardenia33",
    "github_repo": "dataset_stl-obj"
  },
  "missing_textures": {
    "count": 0,
    "file_path_to_color": {},
    "files": []
  },
  "object_count": 4,
  "poly_count": 280,
  "random_color": [
    0.8,
    0.8,
    0.8,
    1
  ],
  "save_uid": "00615912.stl",
  "scene_size": {
    "bbox_max": [
      0.07221128046512604,
      0.75,
      0.051024362444877625
    ],
    "bbox_min": [
      -0.1829105168581009,
      -0.2704872190952301,
      -1.656256461325537e-17
    ]
  },
  "sha256": "2a66401f26e7d2de78a9ccdcb2484a4988cc540502723cf6a378aad63e8c4b2b",
  "shape_key_count": 0,
  "vert_count": 132
}