{
  "animation_count": 0,
  "armature_count": 0,
  "edge_count": 30,
  "file_identifier": "https://github.com/Gardenia33/dataset_stl-obj/blob/main/cad_obj_test_fushion360gallery_reconstruction/22606_f1813fe7_0006.obj",
  "file_size": 1592,
  "lamp_count": 1,
  "linked_files": [],
  "material_count": 1,
  "mesh_count": 1,
  "metadata": {
    "github_organization": "Gardenia33",
    "github_repo": "dataset_stl-obj"
  },
  "missing_textures": {
    "count": 0,
    "file_path_to_color": {},
    "files": []
  },
  "object_count": 4,
  "poly_count": 12,
  "random_color": null,
  "save_uid": "22606_f1813fe7_0006",
  "scene_size": {
    "bbox_max": [
      2.9811999797821045,
      0.0,
      0.20000000298023224
    ],
    "bbox_min": [
      0.0,
      -4.4766998291015625,
      -1.9568275888559583e-07
    ]
  },
  "sha256": "0d60c35acddc4f28e95741eb03236c5b0beb7717246016dcd9cd1112e6873816",
  "shape_key_count": 0,
  "vert_count": 24
}