{
  "animation_count": 0,
  "armature_count": 0,
  "edge_count": 4188,
  "file_identifier": "https://github.com/fazhihe/WHUCAD/blob/main/data/brep/0101/100001812.stl",
  "file_size": 759647,
  "lamp_count": 1,
  "linked_files": [],
  "material_count": 0,
  "mesh_count": 1,
  "metadata": {
    "github_organization": "fazhihe",
    "github_repo": "WHUCAD"
  },
  "missing_textures": {
    "count": 0,
    "file_path_to_color": {},
    "files": []
  },
  "object_count": 4,
  "poly_count": 2792,
  "random_color": [
    0.8,
    0.8,
    0.8,
    1
  ],
  "save_uid": "100001812.stl",
  "scene_size": {
    "bbox_max": [
      0.5324193239212036,
      0.30289238691329956,
      0.046875
    ],
    "bbox_min": [
      -0.21578949689865112,
      -0.11872120201587677,
      0.0
    ]
  },
  "sha256": "aa8bb8a947becba91c1964af1cf933838f4e922a7cd2a21add0a819f98cbbf46",
  "shape_key_count": 0,
  "vert_count": 1396
}