{
  "animation_count": 0,
  "armature_count": 0,
  "edge_count": 600,
  "file_identifier": "https://github.com/Gardenia33/dataset_stl-obj/blob/main/cad_json_stl_output/0075/00752806.stl",
  "file_size": 20084,
  "lamp_count": 1,
  "linked_files": [],
  "material_count": 0,
  "mesh_count": 1,
  "metadata": {
    "github_organization": "Gardenia33",
    "github_repo": "dataset_stl-obj"
  },
  "missing_textures": {
    "count": 0,
    "file_path_to_color": {},
    "files": []
  },
  "object_count": 4,
  "poly_count": 400,
  "random_color": [
    0.8,
    0.8,
    0.8,
    1
  ],
  "save_uid": "00752806.stl",
  "scene_size": {
    "bbox_max": [
      0.1607142835855484,
      0.16069485247135162,
      0.75
    ],
    "bbox_min": [
      -0.1606365442276001,
      -0.16069485247135162,
      0.0
    ]
  },
  "sha256": "99443a1d95edd8b435de74a85d048c5294601c3737bb89e647b72d27ecf1346b",
  "shape_key_count": 0,
  "vert_count": 202
}