{
  "animation_count": 0,
  "armature_count": 0,
  "edge_count": 18,
  "file_identifier": "https://github.com/Gardenia33/dataset_stl-obj/blob/main/cad_json_stl_output/0072/00721609.stl",
  "file_size": 684,
  "lamp_count": 1,
  "linked_files": [],
  "material_count": 0,
  "mesh_count": 1,
  "metadata": {
    "github_organization": "Gardenia33",
    "github_repo": "dataset_stl-obj"
  },
  "missing_textures": {
    "count": 0,
    "file_path_to_color": {},
    "files": []
  },
  "object_count": 4,
  "poly_count": 12,
  "random_color": [
    0.8,
    0.8,
    0.8,
    1
  ],
  "save_uid": "00721609.stl",
  "scene_size": {
    "bbox_max": [
      8.230803907531656e-16,
      9.860761315262648e-32,
      0.75
    ],
    "bbox_min": [
      -0.75,
      -0.75,
      0.0
    ]
  },
  "sha256": "7d9d01be1c0b622e24a780161635f174e21341ccca6a4d87b64bd5da1d5c67e0",
  "shape_key_count": 0,
  "vert_count": 8
}