{
  "animation_count": 0,
  "armature_count": 0,
  "edge_count": 18,
  "file_identifier": "https://github.com/Gardenia33/dataset_stl-obj/blob/main/cad_json_stl_output/0068/00682829.stl",
  "file_size": 684,
  "lamp_count": 1,
  "linked_files": [],
  "material_count": 0,
  "mesh_count": 1,
  "metadata": {
    "github_organization": "Gardenia33",
    "github_repo": "dataset_stl-obj"
  },
  "missing_textures": {
    "count": 0,
    "file_path_to_color": {},
    "files": []
  },
  "object_count": 4,
  "poly_count": 12,
  "random_color": [
    0.8,
    0.8,
    0.8,
    1
  ],
  "save_uid": "00682829.stl",
  "scene_size": {
    "bbox_max": [
      6.661338147750939e-16,
      0.75,
      0.03688524663448334
    ],
    "bbox_min": [
      -0.6516393423080444,
      0.0,
      0.0
    ]
  },
  "sha256": "5c818f560ce4fb3f1f337607462d4b6f450ccdf686379498d739ddef43bcb011",
  "shape_key_count": 0,
  "vert_count": 8
}