{
  "animation_count": 0,
  "armature_count": 0,
  "edge_count": 114,
  "file_identifier": "https://github.com/Gardenia33/dataset_stl-obj/blob/main/cad_json_stl_output/0000/00001907.stl",
  "file_size": 3884,
  "lamp_count": 1,
  "linked_files": [],
  "material_count": 0,
  "mesh_count": 1,
  "metadata": {
    "github_organization": "Gardenia33",
    "github_repo": "dataset_stl-obj"
  },
  "missing_textures": {
    "count": 0,
    "file_path_to_color": {},
    "files": []
  },
  "object_count": 4,
  "poly_count": 76,
  "random_color": [
    0.8,
    0.8,
    0.8,
    1
  ],
  "save_uid": "00001907.stl",
  "scene_size": {
    "bbox_max": [
      0.75,
      7.1205808829065e-16,
      0.5331819653511047
    ],
    "bbox_min": [
      -0.034136585891246796,
      -0.2161983698606491,
      -0.3078489601612091
    ]
  },
  "sha256": "8b18498cd243b83f2bdd0cefc49e0409fb46dae6537eb377dcf57a3d6a28e362",
  "shape_key_count": 0,
  "vert_count": 40
}